AUTHORS
CHANGELOG.txt
DESCRIPTION
LICENSE
MANIFEST.in
README.rst
setup.cfg
setup.py
django_multilingual_tags.egg-info/PKG-INFO
django_multilingual_tags.egg-info/SOURCES.txt
django_multilingual_tags.egg-info/dependency_links.txt
django_multilingual_tags.egg-info/requires.txt
django_multilingual_tags.egg-info/top_level.txt
multilingual_tags/__init__.py
multilingual_tags/admin.py
multilingual_tags/models.py
multilingual_tags/forms/__init__.py
multilingual_tags/forms/mixins.py
multilingual_tags/migrations/0001_initial.py
multilingual_tags/migrations/__init__.py
multilingual_tags/south_migrations/0001_initial.py
multilingual_tags/south_migrations/0002_auto__add_field_taggeditem_user.py
multilingual_tags/south_migrations/__init__.py
multilingual_tags/static/.empty
multilingual_tags/static/multilingual_tags/.empty
multilingual_tags/static/multilingual_tags/css/typeahead.tagging.css
multilingual_tags/static/multilingual_tags/css/typeahead.tagging.less
multilingual_tags/static/multilingual_tags/js/typeahead.bundle.min.js
multilingual_tags/static/multilingual_tags/js/typeahead.tagging.js
multilingual_tags/static/multilingual_tags/js/typeahead.tagging.min.js
multilingual_tags/templates/multilingual_tags/.empty
multilingual_tags/tests/__init__.py
multilingual_tags/tests/forms_mixins_tests.py
multilingual_tags/tests/models_tests.py
multilingual_tags/tests/settings.py
multilingual_tags/tests/test_settings.py
multilingual_tags/tests/test_app/__init__.py
multilingual_tags/tests/test_app/admin.py
multilingual_tags/tests/test_app/forms.py
multilingual_tags/tests/test_app/models.py
multilingual_tags/tests/test_app/urls.py
multilingual_tags/tests/test_app/templates/400.html
multilingual_tags/tests/test_app/templates/500.html