Metadata-Version: 1.0
Name: django-multilingual-tags
Version: 0.9.1
Summary: A reusable Django app that allows you to add translatable tags to any other model.
